common/__init__.py
common/client.py
common/client_server.py
common/server.py
common/tc_logging.py
common/util.py
common/view.py
csta/CstaApplication.py
csta/CstaEndpoint.py
csta/CstaFlows.py
csta/CstaMessage.py
csta/CstaParser.py
csta/CstaUser.py
csta/__init__.py
csta/CstaPool/ClearConnection.xml
csta/CstaPool/ClearConnectionResponse.xml
csta/CstaPool/ConnectionClearedEvent.xml
csta/CstaPool/DeliveredEvent.xml
csta/CstaPool/EstablishedEvent.xml
csta/CstaPool/MakeCall.xml
csta/CstaPool/MakeCallResponse.xml
csta/CstaPool/MonitorStart.xml
csta/CstaPool/MonitorStartResponse.xml
csta/CstaPool/OriginatedEvent.xml
csta/CstaPool/ServiceInitiatedEvent.xml
csta/CstaPool/SnapshotDevice.xml
csta/CstaPool/SnapshotDeviceResponse.xml
csta/CstaPool/SystemRegister.xml
csta/CstaPool/SystemRegisterResponse.xml
csta/CstaPool/SystemStatus.xml
csta/CstaPool/SystemStatusResponse.xml
csta/CstaPool/SystemStatus_RegisterID.xml
sip/SipEndpoint.py
sip/SipFlows.py
sip/SipMessage.py
sip/SipParser.py
sip/__init__.py
sip/messages.py
tshark_tools/__init__.py
tshark_tools/analyze_gui.py
tshark_tools/check_trace.py
tshark_tools/describe.py
tshark_tools/diff.py
tshark_tools/lib.py
tshark_tools/tc_data.py
tshark_tools/test.py
tshark_tools/test_flow.py
tshark_tools/test_generator.py
pyssimist-1.0.3.dist-info/LICENSE
pyssimist-1.0.3.dist-info/METADATA
pyssimist-1.0.3.dist-info/WHEEL
pyssimist-1.0.3.dist-info/top_level.txt
pyssimist-1.0.3.dist-info/RECORD
